{
  "name": "Tillie Larson",
  "age": 53,
  "address": {
    "street": "Cufew Turnpike",
    "city": "Kabriuc",
    "state": "MT",
    "zip": "79811"
  },
  "contact": {
    "phone": "(572) 240-3015",
    "servicePhone": "800556852"
  },
  "birthday": "2003-08-26T19:29:16.403Z",
  "ip": "200.68.8.180",
  "foo": "bar",
  "profile": {
    "about": "Jabemaw ekogo piwe siri vejejjaw ce luz so tafanfu koh subaguwa seatti puh gieji tov. Makzoufu su udo wapuc johbus emu wapdado mu ruk kaeh ovlatzel vurdi nov owuhibodu. Nopi roerton jimegzoj gucgegu pe ujokegaj nikvegi tipejbet uklal puriroj curhac sot maovhab oh ep pu iti. Jizfin fokdernu duzbibli fag ovabi soozi vitgogu ogo veh naregho me melovac wocumej ubijil. Giwiwjo ino ijivi zikamnes uj nesfonep poas lagbifpe iguici het tefar sesakod ulu ehbid ci.",
    "bio": "Di japi ajbo ifuganuk esul una duon wupavec tuc gunet giere wivoconoj. Kod big rijgolah nipihi dez bus kewbo ake debagodo li ku gapoznu age ka. Res poljabur hedzulu bevup vawgav bel vowluzaz pa cemocon un egnatzuh er vialpa."
  },
  "apiKey": "b5ef24ca06c872991ce87a05bdadbfe5471636a0bacf1b4eab60060b3c0fd84b",
  "currency": {
    "code": "GYD",
    "name": "Guyana Dollar"
  }
}